{
  "id":3,
  "name":"Employment and Support Allowance (ESA)",
  "description": "Lets customers who are unable to work through sickness or injury make a claim for Employment and Support Allowance.",
  "theme": "Health & Disability",
  "location": "Leeds",
  "phase":"beta",
  "phase_modifier":"Private",
  "sro":"Justin Russell",
  "service_man":"Adam Tostevin",
  "phase-history":{
    "discovery": [
      {"label":"Completed", "date": "January 2016"}
    ],
  "alpha": [
      {"label":"Completed", "date": "July 2016"}
    ],
    "beta": [
      {"label":"Started", "date": "July 2016"},
      {"label":"Private beta started", "date": "September 2016"}
    ]
  },

  "priority":"TBC",
  "prototype":"http://esa-digital.herokuapp.com"
}
